mal4py/__init__.py
mal4py/_basic.py
mal4py/_media.py
mal4py/_query.py
mal4py/_utils.py
mal4py-0.1.4.dist-info/LICENSE
mal4py-0.1.4.dist-info/METADATA
mal4py-0.1.4.dist-info/WHEEL
mal4py-0.1.4.dist-info/top_level.txt
mal4py-0.1.4.dist-info/RECORD
