Metadata-Version: 2.1
Name: mal4py
Version: 0.1.4
Summary: MAL API An unofficial MyAnimeList API for Python 3
Author-email: Tony White <tony.white_dev@proton.me>
Maintainer-email: antoblanco <tony.white_dev@proton.me>
License: MIT License
Project-URL: Homepage, https://github.com/AntoBlanco/MAL4Py
Project-URL: Bug Tracker, https://github.com/AntoBlanco/MAL4Py/issues
Keywords: api,myanimelist,MAL,Anime,Manga
Classifier: Programming Language :: Python :: 3
Classifier: License :: OSI Approved :: MIT License
Classifier: Operating System :: OS Independent
Requires-Python: >=3.9
License-File: LICENSE
